Convalt.py
convalt-1.1.0.dist-info/licenses/LICENSE
convalt-1.1.0.dist-info/METADATA
convalt-1.1.0.dist-info/WHEEL
convalt-1.1.0.dist-info/top_level.txt
convalt-1.1.0.dist-info/RECORD
