Metadata-Version: 2.4
Name: convalt
Version: 1.1.0
Summary: A universal format converter for images and audio files
Home-page: https://github.com/mochacinno-dev/Convalt
Author: Camila 'Mocha' Rose
Author-email: Camila 'Mocha' Rose <rblossom.dev@gmail.com>
License: MIT
Project-URL: Homepage, https://github.com/mochacinno-dev/Convalt
Project-URL: Documentation, https://github.com/mochacinno-dev/Convalt
Project-URL: Repository, https://github.com/mochacinno-dev/Convalt
Project-URL: Issues, https://github.com/mochacinno-dev/Convalt/issues
Keywords: converter,image,audio,format,conversion,convalt
Classifier: Development Status :: 4 - Beta
Classifier: Intended Audience :: Developers
Classifier: Topic :: Multimedia :: Sound/Audio :: Conversion
Classifier: Topic :: Multimedia :: Graphics :: Graphics Conversion
Classifier: License :: OSI Approved :: MIT License
Classifier: Programming Language :: Python :: 3
Requires-Python: >=3.7
License-File: LICENSE
Requires-Dist: Pillow>=10.0.0
Requires-Dist: pydub>=0.25.0
Dynamic: author
Dynamic: home-page
Dynamic: license-file
Dynamic: requires-python
